relperm/__init__.py
relperm/relperm.py
relperm-0.1.3.dist-info/WHEEL
relperm-0.1.3.dist-info/METADATA
relperm-0.1.3.dist-info/RECORD
