Metadata-Version: 2.3
Name: relperm
Version: 0.1.3
Summary: Add your description here
Requires-Dist: numpy>=2.3.2
Requires-Python: >=3.12
